Metadata-Version: 2.1
Name: video-stabilizer
Version: 0.1
Summary: A minimal package for video stabilization
Home-page: https://github.com/sartorius-research/video_stabilizer
Author: Rickard Sjoegren
Author-email: rickard.sjoegren@sartorius.com
License: UNKNOWN
Platform: UNKNOWN
Classifier: Programming Language :: Python :: 3
Classifier: License :: OSI Approved :: MIT License
Classifier: Operating System :: OS Independent
Requires-Python: >=3.6
